{
  "generated_at": "2026-03-13T10:00:00+00:00",
  "instances": [
    { "business_line": "a3i",      "env": "dev",  "url": "starburst-a101731-dev-8614e238",    "number_of_catalogs": 2,  "healthy_catalogs": 2,  "coordinator_uptime": "10.58d", "coordinator_health": true,  "number_of_workers": 2, "workers_health": true,  "version": "474-e.8", "starburst_instance_health": true,  "errors": null, "failed_catalogs": null },
    { "business_line": "arval",    "env": "dev",  "url": "starburst-ap50708-dev-0a1358eb",    "number_of_catalogs": 7,  "healthy_catalogs": 7,  "coordinator_uptime": "1.70d",  "coordinator_health": true,  "number_of_workers": 2, "workers_health": true,  "version": "474-e.8", "starburst_instance_health": true,  "errors": null, "failed_catalogs": null },
    { "business_line": "arval",    "env": "qual", "url": "starburst-ap50708-qual-becd3da2",   "number_of_catalogs": 6,  "healthy_catalogs": 6,  "coordinator_uptime": "1.69d",  "coordinator_health": true,  "number_of_workers": 2, "workers_health": true,  "version": "474-e.8", "starburst_instance_health": true,  "errors": null, "failed_catalogs": null },
    { "business_line": "bcef",     "env": "dev",  "url": "starburst-ap80414-dev-8d8300e8",    "number_of_catalogs": 21, "healthy_catalogs": 15, "coordinator_uptime": "10.55d", "coordinator_health": true,  "number_of_workers": 3, "workers_health": true,  "version": "474-e.8", "starburst_instance_health": true,  "errors": "-", "failed_catalogs": ["cat_ap12181_test_dse", "cat_ap19368_pole_mg", "cat_ap80414_proxy_hdp", "cat_ap80414_proxy_idf_tdf", "cat_ap80414_proxy_td", "cat_test_hdp_proxy_hdp"] },
    { "business_line": "bcef",     "env": "qual", "url": "starburst-ap80414-qual-d17611c5",   "number_of_catalogs": 12, "healthy_catalogs": 11, "coordinator_uptime": "6.65d",  "coordinator_health": true,  "number_of_workers": 5, "workers_health": true,  "version": "474-e.8", "starburst_instance_health": true,  "errors": "-", "failed_catalogs": ["cat_ap80414_proxy_td"] },
    { "business_line": "bnl",      "env": "dev",  "url": "starburst-ap84264-dev-4a6a05e9",    "number_of_catalogs": 20, "healthy_catalogs": 20, "coordinator_uptime": "10.58d", "coordinator_health": true,  "number_of_workers": 2, "workers_health": true,  "version": "474-e.8", "starburst_instance_health": true,  "errors": null, "failed_catalogs": null },
    { "business_line": "bnl",      "env": "qual", "url": "starburst-ap84264-qual-a7441a77",   "number_of_catalogs": 22, "healthy_catalogs": 22, "coordinator_uptime": "1.93d",  "coordinator_health": true,  "number_of_workers": 5, "workers_health": true,  "version": "474-e.8", "starburst_instance_health": true,  "errors": null, "failed_catalogs": null },
    { "business_line": "cardif",   "env": "dev",  "url": "starburst-ap63215-dev-8850c885",    "number_of_catalogs": 45, "healthy_catalogs": 43, "coordinator_uptime": "9.83d",  "coordinator_health": true,  "number_of_workers": 3, "workers_health": true,  "version": "474-e.8", "starburst_instance_health": true,  "errors": "-", "failed_catalogs": ["dhcpw_dev_c1_ora", "maestro_x2_dev_c1_ora"] },
    { "business_line": "cardif",   "env": "int",  "url": "starburst-ap63215-int-8685f0e4",    "number_of_catalogs": 38, "healthy_catalogs": 37, "coordinator_uptime": "15.82d", "coordinator_health": true,  "number_of_workers": 3, "workers_health": true,  "version": "474-e.8", "starburst_instance_health": true,  "errors": "-", "failed_catalogs": ["dhcpw_int_c1_ora"] },
    { "business_line": "cardif",   "env": "qual", "url": "starburst-ap63215-qual-08b96cc9",   "number_of_catalogs": 40, "healthy_catalogs": 40, "coordinator_uptime": "10.58d", "coordinator_health": true,  "number_of_workers": 3, "workers_health": true,  "version": "474-e.8", "starburst_instance_health": true,  "errors": null, "failed_catalogs": null },
    { "business_line": "embmci",   "env": "dev",  "url": "starburst-ap84088-dev-7e52210a",    "number_of_catalogs": 6,  "healthy_catalogs": 6,  "coordinator_uptime": "10.58d", "coordinator_health": true,  "number_of_workers": 2, "workers_health": true,  "version": "474-e.8", "starburst_instance_health": true,  "errors": null, "failed_catalogs": null },
    { "business_line": "embmci",   "env": "qual", "url": "starburst-a100771-qual-a27401ad",   "number_of_catalogs": 2,  "healthy_catalogs": 2,  "coordinator_uptime": "10.58d", "coordinator_health": true,  "number_of_workers": 2, "workers_health": true,  "version": "474-e.8", "starburst_instance_health": true,  "errors": null, "failed_catalogs": null },
    { "business_line": "fortis",   "env": "dev",  "url": "starburst-ap84611-dev-8fa503a9",    "number_of_catalogs": 5,  "healthy_catalogs": 4,  "coordinator_uptime": "3.69d",  "coordinator_health": true,  "number_of_workers": 2, "workers_health": true,  "version": "474-e.8", "starburst_instance_health": true,  "errors": "-", "failed_catalogs": ["orion_hdp"] },
    { "business_line": "fortis",   "env": "qual", "url": "starburst-ap84611-qual-3e6ebeef",   "number_of_catalogs": 4,  "healthy_catalogs": 4,  "coordinator_uptime": "1.69d",  "coordinator_health": true,  "number_of_workers": 3, "workers_health": true,  "version": "474-e.8", "starburst_instance_health": true,  "errors": null, "failed_catalogs": null },
    { "business_line": "fresh",    "env": "dev",  "url": "starburst-ap84088-dev-7e52210a",    "number_of_catalogs": 6,  "healthy_catalogs": 6,  "coordinator_uptime": "10.58d", "coordinator_health": true,  "number_of_workers": 2, "workers_health": true,  "version": "474-e.8", "starburst_instance_health": true,  "errors": null, "failed_catalogs": null },
    { "business_line": "ichrom",   "env": "dev",  "url": "starburst-ap84088-dev-7e52210a",    "number_of_catalogs": 6,  "healthy_catalogs": 6,  "coordinator_uptime": "10.58d", "coordinator_health": true,  "number_of_workers": 2, "workers_health": true,  "version": "474-e.8", "starburst_instance_health": true,  "errors": null, "failed_catalogs": null },
    { "business_line": "ichrom",   "env": "qual", "url": "starburst-ap84611-qual-3e6ebeef",   "number_of_catalogs": 4,  "healthy_catalogs": 4,  "coordinator_uptime": "1.69d",  "coordinator_health": true,  "number_of_workers": 3, "workers_health": true,  "version": "474-e.8", "starburst_instance_health": true,  "errors": null, "failed_catalogs": null },
    { "business_line": "opendata", "env": "dev",  "url": "starburst-ap25711-dev-f3e6de45",    "number_of_catalogs": 25, "healthy_catalogs": 25, "coordinator_uptime": "10.58d", "coordinator_health": true,  "number_of_workers": 2, "workers_health": true,  "version": "474-e.8", "starburst_instance_health": true,  "errors": null, "failed_catalogs": null },
    { "business_line": "wm",       "env": "dev",  "url": "starburst-ap92045-dev-784737e9",    "number_of_catalogs": 9,  "healthy_catalogs": 7,  "coordinator_uptime": "3.73d",  "coordinator_health": true,  "number_of_workers": 2, "workers_health": true,  "version": "474-e.8", "starburst_instance_health": true,  "errors": "-", "failed_catalogs": ["test_wmdatahub_pg", "wmdatahub_pg"] },
    { "business_line": "wm",       "env": "int",  "url": "starburst-ap92045-int-f21db8bc",    "number_of_catalogs": 6,  "healthy_catalogs": 6,  "coordinator_uptime": "2.92d",  "coordinator_health": true,  "number_of_workers": 2, "workers_health": true,  "version": "474-e.8", "starburst_instance_health": true,  "errors": null, "failed_catalogs": null },
    { "business_line": "wm",       "env": "qual", "url": "starburst-ap92045-qual-1dfbfe69",   "number_of_catalogs": 2,  "healthy_catalogs": 2,  "coordinator_uptime": "10.58d", "coordinator_health": true,  "number_of_workers": 2, "workers_health": true,  "version": "474-e.8", "starburst_instance_health": true,  "errors": null, "failed_catalogs": null }
  ]
}
